ida_pro_mcp/fuckery.py
ida_pro_mcp/mcp-plugin.py
ida_pro_mcp/server.py
ida_pro_mcp/server_generated.py
ida_pro_mcp-1.3.0.dist-info/licenses/LICENSE
ida_pro_mcp-1.3.0.dist-info/METADATA
ida_pro_mcp-1.3.0.dist-info/WHEEL
ida_pro_mcp-1.3.0.dist-info/entry_points.txt
ida_pro_mcp-1.3.0.dist-info/top_level.txt
ida_pro_mcp-1.3.0.dist-info/RECORD
