Metadata-Version: 2.4
Name: ida-pro-mcp
Version: 1.3.0
Summary: Vibe reversing with IDA Pro
Author: mrexodia
Project-URL: Repository, https://github.com/mrexodia/ida-pro-mcp
Project-URL: Issues, https://github.com/mrexodia/ida-pro-mcp/issues
Keywords: ida,mcp,llm,plugin
Classifier: Development Status :: 5 - Production/Stable
Classifier: Intended Audience :: Developers
Classifier: Programming Language :: Python :: 3
Classifier: Programming Language :: Python :: 3.11
Classifier: Operating System :: MacOS
Classifier: Operating System :: Microsoft :: Windows
Requires-Python: >=3.11
License-File: LICENSE
Requires-Dist: mcp>=1.6.0
Dynamic: license-file
